{
  "name": "1.json",
  "created_at": "2025-04-07T16:35:04.340474",
  "events": [
    {
      "type": "mouse",
      "event_type": "down",
      "button": "left",
      "time": 0.3278689384460449,
      "position": [
        2342,
        1207
      ],
      "is_relative": false
    },
    {
      "type": "delay",
      "time": 0.39793293380737305,
      "delay": 0.07106399536132812
    },
    {
      "type": "mouse",
      "event_type": "up",
      "button": "left",
      "time": 0.39893293380737305,
      "position": [
        2342,
        1207
      ],
      "is_relative": false
    },
    {
      "type": "delay",
      "time": 0.6271783580780029,
      "delay": 0.22924542427062988
    },
    {
      "type": "mouse",
      "event_type": "double",
      "button": "left",
      "time": 0.6281783580780029,
      "position": [
        2613,
        1359
      ],
      "is_relative": false
    },
    {
      "type": "delay",
      "time": 0.7052397003173828,
      "delay": 0.07806134223937988
    },
    {
      "type": "mouse",
      "event_type": "up",
      "button": "left",
      "time": 0.7062397003173828,
      "position": [
        2613,
        1360
      ],
      "is_relative": false
    },
    {
      "type": "delay",
      "time": 2.0837036838531495,
      "delay": 1.3784639835357666
    },
    {
      "type": "mouse",
      "event_type": "down",
      "button": "left",
      "time": 2.0847036838531494,
      "position": [
        1837,
        895
      ],
      "is_relative": false
    },
    {
      "type": "delay",
      "time": 2.1678308715820314,
      "delay": 0.08412718772888184
    },
    {
      "type": "mouse",
      "event_type": "up",
      "button": "left",
      "time": 2.1688308715820312,
      "position": [
        1837,
        895
      ],
      "is_relative": false
    }
  ]
}